commonnexus/__init__.py
commonnexus/__main__.py
commonnexus/cli_util.py
commonnexus/command.py
commonnexus/nexus.py
commonnexus/tokenizer.py
commonnexus/util.py
commonnexus/blocks/__init__.py
commonnexus/blocks/assumptions.py
commonnexus/blocks/base.py
commonnexus/blocks/characters.py
commonnexus/blocks/codons.py
commonnexus/blocks/distances.py
commonnexus/blocks/notes.py
commonnexus/blocks/sets.py
commonnexus/blocks/taxa.py
commonnexus/blocks/trees.py
commonnexus/blocks/unaligned.py
commonnexus/commands/__init__.py
commonnexus/commands/characters.py
commonnexus/commands/combine.py
commonnexus/commands/help.py
commonnexus/commands/normalise.py
commonnexus/commands/split.py
commonnexus/commands/taxa.py
commonnexus/commands/trees.py
commonnexus/tools/__init__.py
commonnexus/tools/combine.py
commonnexus/tools/matrix.py
commonnexus/tools/normalise.py
commonnexus-1.9.2.dist-info/LICENSE
commonnexus-1.9.2.dist-info/METADATA
commonnexus-1.9.2.dist-info/WHEEL
commonnexus-1.9.2.dist-info/entry_points.txt
commonnexus-1.9.2.dist-info/top_level.txt
commonnexus-1.9.2.dist-info/RECORD
